syft_client/__init__.py
syft_client/environment.py
syft_client/syft_client.py
syft_client/auth/__init__.py
syft_client/auth/wallets/__init__.py
syft_client/auth/wallets/base.py
syft_client/auth/wallets/local_file.py
syft_client/platforms/__init__.py
syft_client/platforms/base.py
syft_client/platforms/detection.py
syft_client/platforms/transport_base.py
syft_client/platforms/apple/__init__.py
syft_client/platforms/apple/client.py
syft_client/platforms/dropbox/__init__.py
syft_client/platforms/dropbox/client.py
syft_client/platforms/dropbox/files.py
syft_client/platforms/fastmail/__init__.py
syft_client/platforms/fastmail/client.py
syft_client/platforms/gmx/__init__.py
syft_client/platforms/gmx/client.py
syft_client/platforms/google_org/__init__.py
syft_client/platforms/google_org/client.py
syft_client/platforms/google_org/gdrive_files.py
syft_client/platforms/google_org/gforms.py
syft_client/platforms/google_org/gmail.py
syft_client/platforms/google_org/gsheets.py
syft_client/platforms/google_org/wizard.py
syft_client/platforms/google_personal/__init__.py
syft_client/platforms/google_personal/client.py
syft_client/platforms/google_personal/gdrive_files.py
syft_client/platforms/google_personal/gforms.py
syft_client/platforms/google_personal/gmail.py
syft_client/platforms/google_personal/gsheets.py
syft_client/platforms/google_personal/wizard.py
syft_client/platforms/mailcom/__init__.py
syft_client/platforms/mailcom/client.py
syft_client/platforms/microsoft/__init__.py
syft_client/platforms/microsoft/client.py
syft_client/platforms/microsoft/ms_forms.py
syft_client/platforms/microsoft/onedrive_files.py
syft_client/platforms/microsoft/outlook.py
syft_client/platforms/proton/__init__.py
syft_client/platforms/proton/client.py
syft_client/platforms/proton/protondrive.py
syft_client/platforms/proton/protonmail.py
syft_client/platforms/smtp/__init__.py
syft_client/platforms/smtp/client.py
syft_client/platforms/smtp/email.py
syft_client/platforms/yahoo/__init__.py
syft2-0.2.8.dist-info/METADATA
syft2-0.2.8.dist-info/WHEEL
syft2-0.2.8.dist-info/top_level.txt
syft2-0.2.8.dist-info/RECORD
